{
    "100420": "無法識別二維碼",
    "114070": "圖標比例",
    "137656": "螢幕翻譯",
    "200053": "深色",
    "226064": "刷新",
    "296773": "（轉換時速度會很慢）",
    "311887": "x軸",
    "367461": "始終顯示陰影提示",
    "373847": "用戶已取消保存",
    "415812": "強制重載",
    "422455": "展示內容優先",
    "426625": "服務下載已取消",
    "431992": "Gif",
    "488711": "啟用開發者模式",
    "504905": "（標籤將只顯示圖標，懸浮查看標題，中鍵或右鍵關閉）",
    "510714": "圖像",
    "512586": "光標提示",
    "512860": "主搜索功能",
    "520181": "全局樣式",
    "557370": "大版本",
    "630368": "eSearch - 錄屏",
    "646136": "記住框選大小",
    "672727": "箭頭",
    "797827": "歷史記錄",
    "839444": "淺色模式",
    "841632": "滑鼠跟隨欄",
    "856917": "只保留",
    "869382": "剪貼板",
    "920292": "自動清除歷史記錄",
    "f00790": "服務正在下載中……",
    "a27b9d": "服務已下載",
    "d9cece": "，正準備安裝相關的依賴，請允許安裝",
    "a5dfc5": "自動搜索",
    "05316a": "截屏搜索",
    "157bfa": "選中搜索",
    "0b98af": "剪貼板搜索",
    "3bbe1d": "失焦關閉",
    "e4ea04": "主頁面",
    "a1644c": "瀏覽器打開",
    "4d21ef": "設置",
    "361c03": "教程幫助",
    "bb3d91": "重啟",
    "8dad30": "退出",
    "7fc388": "已經在後台啟動",
    "43c388": "服務未下載",
    "e62efd": "離線OCR 服務未安裝",
    "e9613d": "需要下載才能使用",
    "fc2b6f": "不再提示",
    "f551c4": "下載(約",
    "b64102": "前往 設置",
    "915c25": "取消",
    "c9d77b": "服務需要升級",
    "d772b8": "離線OCR 服務版本較舊",
    "6b9e40": "服務下載失敗",
    "142fad": "離線OCR 服務版本下載失敗",
    "dff6c5": "請前往網站手動下載",
    "a7cba0": "警告",
    "c217a1": "請嘗試重新識別",
    "31266f": "選擇要打開應用的位置",
    "e6f61e": "選擇要保存的位置",
    "8ba3ff": "保存圖像失敗",
    "466d02": "FFmpeg 位置錯誤",
    "a25f4d": "FFmpeg 位置錯誤，請在設置裡更正",
    "d42d6d": "FFmpeg 未下載",
    "4ec369": "解壓並填寫路徑到設置",
    "e2b011": "視頻",
    "cd1f7b": "保存視頻失敗",
    "1f971b": "錯誤",
    "f994c3": "已恢復默認設置，部分設置需要重啟",
    "07d034": "稍後",
    "d6d217": "關於",
    "308f4c": "服務",
    "adbfe7": "隱藏",
    "86c57a": "隱藏其他",
    "799cb4": "全部顯示",
    "eecae2": "文件",
    "c367a3": "保存到歷史記錄",
    "26e780": "其他編輯器打開",
    "06029c": "打開方式...",
    "80febf": "關閉",
    "7c17cf": "編輯",
    "92ba64": "打開鏈接",
    "4db992": "搜索",
    "08b3b2": "翻譯",
    "28cf58": "撤銷",
    "c71843": "重做",
    "3ea848": "剪切",
    "8158b1": "複製",
    "f6791f": "粘貼",
    "9ba970": "刪除",
    "da95e0": "全選",
    "7beb05": "自動刪除換行",
    "717a2f": "查找",
    "f293bd": "替換",
    "ac5d63": "自動換行",
    "3622a2": "拼寫檢查",
    "72618d": "朗讀",
    "58f01a": "開始朗讀",
    "6df0a3": "停止朗讀",
    "9a6720": "瀏覽器",
    "cf5355": "後退",
    "675cdc": "前進",
    "ea1616": "停止加載",
    "d2f548": "視圖",
    "8bf00b": "重新加載",
    "7a8686": "開發者工具",
    "5343cf": "實際大小",
    "0a63ee": "放大",
    "bf0673": "縮小",
    "556e0b": "全屏",
    "20fbbd": "窗口",
    "aa3f2e": "最小化",
    "5873c6": "置於最前面",
    "15f366": "幫助",
    "2141e3": "保存圖像成功",
    "ee5187": "已保存圖像到",
    "a2a240": "eSearch - 主页面",
    "93596e": "eSearch - 截屏",
    "62cbc6": "eSearch - 設置",
    "7192b2": "eSearch - 幫助",
    "995f03": "eSearch - 瀏覽器",
    "87009e": "eSearch - ding",
    "8ba34e": "上一個匹配",
    "af5d23": "下一個匹配",
    "b89dc1": "啟動",
    "c44dde": "開機自啟動",
    "b8cceb": "啟動提示",
    "ce6f6b": "啟動時系統通知提示啟動",
    "7f708b": "語言",
    "dc49a4": "使用系統語言",
    "113fe0": "重啟軟件以生效",
    "fb4a9b": "快捷鍵",
    "356a55": "全局",
    "45a6ae": "截屏",
    "6b805f": "自動識別",
    "dda425": "複製顏色",
    "3238c2": "自動搜索排除",
    "a1a8c2": "若選中的文字符合文本框的規則，將使用截屏搜索而不是選擇搜索",
    "0135ad": "換行新建項目，支持正則表達式",
    "d9ab9c": "使用選區內容",
    "daf0c7": "毛玻璃效果",
    "8511bd": "模糊",
    "d0998d": "不透明度",
    "fa90f9": "深色模式",
    "3c0020": "跟隨系統",
    "94b955": "淺色",
    "abd5b8": "全局縮放",
    "17cf1b": "字體",
    "9b2f76": "主要字體",
    "c89ac4": "（適用於主页面等文字字體）",
    "1bf383": "等寬字體",
    "923f29": "（適用於截屏時數字、顏色代碼等字體）",
    "0cae0a": "工具欄",
    "fa9bc1": "工具欄跟隨",
    "f3651b": "效率優先",
    "c077b3": "按鈕大小",
    "cab8c7": "按鈕",
    "a5c9f3": "取色器",
    "2350b2": "大小",
    "68e19c": "取色器大小",
    "c24d71": "像素大小",
    "95a455": "默認格式",
    "ae93c3": "框選",
    "58ae3d": "框選顏色",
    "e98d3b": "遮罩顏色",
    "9f27ea": "選區顏色",
    "f8ab11": "光標",
    "6de41a": "以(0,0)為起點",
    "77b02d": "以(1,1)為起點",
    "7f8ccc": "大小坐標",
    "9c585f": "顯示四角坐標",
    "15b7f5": "（截屏框選附近除了框選大小，還會加上左上角和右下角坐標）",
    "3e637a": "框選後默認操作",
    "61202b": "框選完鼠標鬆開一瞬間，執行操作",
    "3ffe54": "無",
    "406b6c": "OCR(文字識別)",
    "bec776": "以圖搜圖",
    "01d309": "QR碼",
    "70e562": "標記",
    "938dc7": "其他應用打開",
    "643b51": "放在屏幕上",
    "6473d3": "保存",
    "1b7c0f": "自動框選",
    "08d128": "使用OpenCV自動識別邊緣輪廓（測試版）",
    "2f0dc5": "啟用自動框選",
    "e63d01": "邊緣識別高級設置",
    "77352c": "最小閾值",
    "c9b364": "最大閾值",
    "3ea83c": "圖像編輯",
    "cd252e": "默認屬性",
    "d1ad51": "填充顏色",
    "01fde8": "邊框顏色",
    "22fc71": "邊框寬度",
    "167ef9": "畫筆顏色",
    "c0a279": "畫筆粗細",
    "35708a": "複製偏移",
    "55ddf7": "複製完一個元素後，為了分辨，可以讓其偏移",
    "7c8c91": "y軸",
    "9b6bad": "貼圖",
    "c8d31a": "窗口變換",
    "5384cb": "變換使用 CSS 代碼",
    "fb5e33": "快速截屏",
    "0565c3": "保存到",
    "be778b": "目錄",
    "6aab2e": "獲取保存路徑",
    "d2f67d": "錄屏",
    "4410dc": "凡是麥克風和攝像頭，都應該當成開著的",
    "ef157b": "自動錄製",
    "c7e4c9": "開啟自動錄製",
    "5a6d24": "錄製",
    "e8fd5a": "視頻比特率",
    "3c5ccd": "提示",
    "e9b225": "開啟鍵盤按鍵提示",
    "70a305": "開啟鼠標按鍵提示",
    "f9b257": "開啟光標提示",
    "60ba1f": "光標提示樣式",
    "56d3bb": "高級",
    "37a754": "攝像頭",
    "29d264": "默認開啟",
    "85da95": "記錄開啟狀態",
    "99d03c": "鏡像",
    "def39f": "音頻",
    "2b2cbf": "轉換",
    "959ca3": "使用 FFmpeg 對錄製的視頻進行轉換工作",
    "3fe77f": "下載 FFmpeg",
    "908bc9": "FFmpeg 位置",
    "8407e0": "自動轉換",
    "f73213": "開啟自動轉換",
    "93acf2": "輸出格式",
    "14a29c": "碼率",
    "92c252": "幀率",
    "5a72b0": "其他參數",
    "001266": "高質量 Gif",
    "b387a2": "文件名稱",
    "0952bb": "預覽:",
    "28fe84": "時間代碼",
    "a9989e": "四位數年",
    "adec4f": "末兩位年",
    "bd8a99": "月",
    "f41ab6": "日",
    "31a95d": "星期",
    "4493db": "24小時制小時",
    "d9fe60": "12小時制小時",
    "ba9fae": "分",
    "860cd9": "秒",
    "0d6a60": "毫秒",
    "7f40ce": "jpg質量",
    "bb9df8": "編輯器",
    "790c3d": "字體大小",
    "b7a153": "記住主页面字體大小",
    "6d32bb": "樣式",
    "8c28c7": "Tab製表符寬度",
    "2d1dd2": "光標動畫時間",
    "e370e9": "更多",
    "c632b9": "行號",
    "579adf": "自動",
    "6758df": "（識屏或直接打開主页面，若文字為一行，則自動搜索）",
    "ebfa2b": "自動打開鏈接",
    "78d79c": "自動搜索中文佔比",
    "00fdd5": "（在中英混合中，數值越小，則整段文字越容易被程序認為是中文主要）",
    "8b623c": "文字搜索引擎",
    "f2a405": "搜索引擎",
    "008b5b": "翻譯引擎",
    "dcd270": "默認引擎",
    "be649e": "記住引擎選擇",
    "d110c6": "圖像搜索引擎",
    "63c20a": "瀏覽器中打開",
    "b79981": "（點擊搜索或翻譯按鈕後，將在系統默認瀏覽器打開搜索結果，否則在一個新的軟件窗口打開）",
    "d46b4b": "瀏覽器打開後自動關閉標籤頁",
    "32e76d": "標籤縮小",
    "d560e5": "標籤圖標灰度",
    "c51e76": "（標籤圖標將以灰度圖片展示，減少多餘顏色的干擾）",
    "e36dc5": "標籤頁透明填充",
    "2e51ef": "（某些透明背景的標籤頁將填充顏色，否則透明顯示，可看見窗口後內容）",
    "6deed0": "文字識別（OCR）",
    "03dd38": "離線OCR",
    "c96fd1": "百度",
    "421d0a": "有道",
    "18ea33": "離線時切換離線OCR",
    "8b8cbd": "OCR檢測",
    "262c86": "（每次啟動時都提示OCR服務是否安裝或開啟）",
    "84935e": "det模型",
    "5f29da": "rec模型",
    "b91439": "字典",
    "43678b": "位置",
    "a937f2": "下載離線OCR",
    "4b942c": "刪除離線OCR",
    "43c416": "在線OCR",
    "71d119": "類型：",
    "bdaab2": "位置版不起實質效果，但可以擴充免費使用次數:)",
    "0b5336": "高精度版",
    "6b2c1d": "高精度含位置版",
    "83fbad": "標準版",
    "c1bda9": "標準含位置版",
    "cdfda4": "手寫文字",
    "229ad3": "公式",
    "a00122": "API Key：",
    "050a36": "Secret Key：",
    "a27196": "應用ID：",
    "ccc1b7": "應用秘鑰：",
    "36214e": "保留截屏記錄",
    "eea497": "不勾選將不限次數保留",
    "74a560": "次記錄",
    "feebe4": "清空所有截屏記錄",
    "e228a6": "保留歷史記錄",
    "2878e2": "天",
    "d620f2": "小時",
    "039aa5": "清空所有文字記錄",
    "261fd6": "日期格式",
    "0e6f53": "代理",
    "5a8301": "開啟代理",
    "cbf8e1": "pac文件：",
    "31a1f8": "代理規則：",
    "b4b8b7": "排除規則：",
    "12e58e": "自動關閉窗口",
    "b2fd3d": "失去焦點後自動關閉",
    "764abb": "高級設置",
    "c9565d": "直接編輯設置源文件，更多自定義設置",
    "bc6613": "（需要JSON知識）",
    "b1ea70": "打開設置源文件",
    "ee532e": "恢復默認設置",
    "5ec65f": "不保存本次設置值",
    "d5534f": "（若不清楚剛才更改了什麼設置，請選中）",
    "df1d42": "硬件加速",
    "f6297b": "啟用硬件加速",
    "0c9c39": "（如果可用，且更改需要重啟軟件生效）",
    "88391e": "檢查更新",
    "508db0": "啟用檢查更新",
    "49275c": "（僅在周末檢查，且只在設置打開時檢查）",
    "85aec0": "位置信息",
    "593d98": "版本信息",
    "1b15cc": "運行目錄：",
    "de46f9": "配置目錄：",
    "eae9a8": "OCR 目錄：",
    "898e8b": "臨時目錄：",
    "79d228": "文字記錄：",
    "d27e74": "截屏記錄：",
    "eaf690": "本機系統內核:",
    "3d6874": "識屏 · 搜索",
    "c88090": "有新版本:",
    "687abb": "暫無更新",
    "89b272": "項目主頁:",
    "d144c6": "更新日誌",
    "e16985": "錯誤報告與建議",
    "0d9ba8": "本軟件遵循",
    "1557e6": "本軟件基於",
    "fd989b": "這些軟件",
    "2619d2": "主頁面模式",
    "13aadb": "長截屏",
    "6b8898": "時間",
    "d0968d": "換行新建專案，%s代替關鍵字",
    "68b620": "選擇與控制",
    "e00bd1": "自由繪畫",
    "973a75": "形狀和文字",
    "796e8e": "濾鏡",
    "448d6b": "矩形框選",
    "944c6b": "自由框選",
    "5f23b1": "繪製",
    "41ed71": "畫筆",
    "8b0e8f": "橡皮",
    "843f9e": "噴刷",
    "8764f3": "線條",
    "c60636": "圓",
    "218fb7": "矩形",
    "57ddb3": "折線",
    "06c6a6": "多邊形",
    "41f06c": "文字",
    "a9db09": "序號",
    "e5310e": "按鈕顯示",
    "24c3ef": "拖曳以控制按鍵順序和顯示",
    "0591be": "左上",
    "60def2": "右上",
    "a842db": "顯示滑鼠跟隨欄",
    "d83fb6": "顯示取色器",
    "87192d": "啟用圖像識別",
    "60fed4": "使用OpenCV自動識別邊緣輪廓",
    "d30e34": "拖曳det模型、rec模型和字典檔到此處",
    "b3eee6": "表格",
    "9cafa2": "背景",
    "078def": "正常",
    "c4667a": "圖片",
    "3372c8": "圖片或視訊填充模式",
    "5c9247": "分段轉換間隔時間",
    "e8f483": "（邊錄製邊轉換以提升效率，0為不分段）",
    "dcfd1c": "快速保存",
    "3b79b2": "按下保存鍵後，默認保存到上次保存的位置，無需選擇",
    "9c5512": "啟用快速保存",
    "30ddb5": "雙擊",
    "5a17b7": "設定雙擊視窗行為",
    "88639e": "失去焦點後自動關閉編輯器",
    "3bc580": "編輯欄",
    "2d1f2a": "其他",
    "64f503": "圖示顏色",
    "2b3943": "系統代理",
    "7e66d1": "固定伺服器",
    "0accc4": "PAC腳本",
    "5b4d1a": "自動檢測",
    "87cf0f": "無代理",
    "c6833c": "檢查測試版更新",
    "b4bbfb": "複製檔案",
    "3f775a": "改進翻譯",
    "ec6dfc": "裁剪適應",
    "1a4b71": "拉伸填充",
    "eed284": "最新版本",
    "79cffb": "點擊下載",
    "571cbd": "增量更新",
    "541f10": "當前版本",
    "04e9d9": "正在更新中",
    "fb67bc": "更新完畢，你可以重啟軟件",
    "60ce0e": "複用主頁面",
    "df58d7": "可加快OCR加載",
    "2dd19e": "圖片區",
    "8e5bb5": "人工智能",
    "a00037": "配置OCR、錄屏背景移除等人工智能",
    "c90e78": "運行後端",
    "f075ab": "鍵盤按鍵提示",
    "5467e1": "偏移x",
    "fd877c": "偏移y",
    "6ce938": "鼠標按鍵提示",
    "5d3e05": "清除數據",
    "e01ad2": "Cookie 等存儲數據",
    "f767c3": "緩存",
    "d26db0": "大小欄",
    "d441ac": "左上x",
    "9d345e": "左上y",
    "ff197c": "右下x",
    "dea24b": "右下y",
    "d55a30": "寬",
    "ad5162": "高",
    "9dbed5": "退出開發者模式",
    "92ca5e": "反饋",
    "b6ad0f": "稍後顯示",
    "9e481f": "支持該項目：",
    "5fb537": "反饋錯誤 提供建議",
    "203af8": "截屏時，工具欄和繪製欄都會隱藏，直到調整完框選",
    "efc978": "啟用",
    "71d90d": "保存時自動複製",
    "22895e": "使用陰影提示貼圖窗口",
    "0619da": "引擎",
    "4203c7": "適用於螢幕翻譯和搜索翻譯，第一個為默認引擎",
    "00f597": "自動翻譯",
    "26a36d": "定時",
    "f1a82a": "高級窗口按鈕",
    "16058a": "如置於最頂層、失去焦點自動關閉按鈕等",
    "38530f": "顯示",
    "53fc86": "顯示/隱藏工具欄、繪製欄",
    "c12b56": "更新頻率",
    "823a26": "更新模式",
    "1dc1e0": "開發者模式",
    "039796": "刪除換行",
    "8ba323": "為項目點亮星標🌟",
    "d7028f": "贊賞",
    "5699dd": "自動顯示圖片區",
    "285d41": "OCR結果行數大於等於該值，自動顯示圖片區。0為不顯示",
    "710ed1": "主題色",
    "5da2d6": "強調色",
    "05ffe0": "截屏背景",
    "9155d4": "其他介面背景",
    "1849f2": "歸位",
    "8691bd": "手動檢查",
    "448f2b": "啟動時檢查",
    "d82774": "小版本",
    "9f3273": "開發版",
    "80758c": "選擇引擎類型",
    "bcc484": "API申請",
    "2ca158": "測試",
    "ce15ca": "完成",
    "864db5": "自動複製OCR結果",
    "f5916c": "箭頭樣式",
    "8d2717": "實心",
    "a6a57e": "空心",
    "d9ef88": "高度",
    "700ce2": "寬度",
    "14d3cc": "參考線",
    "84c360": "光標參考線",
    "e92a94": "光標參考線顏色",
    "ca39e5": "選區參考線x",
    "58236a": "選區參考線y",
    "e3b197": "選區參考線顏色",
    "bf2411": "九宮格",
    "79d1ab": "黃金比例"
}
